schema/InsightEngineResponse.json
schema/__init__.py
schema/claim1.json
schema/claim_topic_message.py
schema/insight_engine_request.py
schema/insight_engine_response.py
schema/insight_engine_testcase.py
schema/legacy/__init__.py
schema/legacy/dsl.py
insight_engine_schema_python-0.3.21.dist-info/LICENSE
insight_engine_schema_python-0.3.21.dist-info/WHEEL
insight_engine_schema_python-0.3.21.dist-info/METADATA
insight_engine_schema_python-0.3.21.dist-info/RECORD
