Metadata-Version: 2.1
Name: insight-engine-schema-python
Version: 0.3.21
Summary: Rialtic insight engine schema in Python
Home-page: https://rialtic.io
License: Apache-2.0
Keywords: rialtic,insight,engines,schema
Author: Rialtic
Author-email: engines.data@rialtic.io
Requires-Python: >=3.7,<4.0
Classifier: Environment :: Console
Classifier: License :: OSI Approved :: Apache Software License
Classifier: Operating System :: OS Independent
Classifier: Programming Language :: Python :: 3
Classifier: Programming Language :: Python :: 3.10
Classifier: Programming Language :: Python :: 3.7
Classifier: Programming Language :: Python :: 3.8
Classifier: Programming Language :: Python :: 3.9
Classifier: Topic :: Software Development :: Libraries :: Python Modules
Requires-Dist: fhir.resources (>=6.0,<7.0)
Project-URL: Repository, https://github.com/rialtic-community/insight-engine-schema-python
